MANIFEST.in
README.rst
setup.py
bft/__init__.py
bft/admin.py
bft/app_settings.py
bft/context_processors.py
bft/forms.py
bft/models.py
bft/urls.py
bft/validators.py
bft/views.py
bft/management/__init__.py
bft/management/commands/__init__.py
bft/management/commands/deletetempfiles.py
bft/management/commands/deleteuploads.py
bft/static/bft/images/bkg-body.png
bft/static/bft/images/bkg-bottom.png
bft/static/bft/images/bkg-inner.png
bft/static/bft/images/bkg-top.png
bft/static/bft/images/button.png
bft/static/bft/images/cancel.png
bft/static/bft/images/choose.png
bft/static/bft/images/icon-email.png
bft/static/bft/images/icon-link.png
bft/static/bft/images/links.png
bft/static/bft/images/logo-bft.png
bft/static/bft/images/overlay.png
bft/static/bft/images/step-1.png
bft/static/bft/images/step-2.png
bft/static/bft/images/step-3.png
bft/static/bft/images/step-4.png
bft/static/bft/images/step-5.png
bft/static/bft/images/step-6.png
bft/static/bft/images/support.gif
bft/static/bft/images/uploadify.swf
bft/static/bft/images/ui/ui-bg_flat_0_aaaaaa_40x100.png
bft/static/bft/images/ui/ui-bg_flat_55_fbec88_40x100.png
bft/static/bft/images/ui/ui-bg_glass_75_d0e5f5_1x400.png
bft/static/bft/images/ui/ui-bg_glass_85_dfeffc_1x400.png
bft/static/bft/images/ui/ui-bg_glass_95_fef1ec_1x400.png
bft/static/bft/images/ui/ui-bg_gloss-wave_0_285583_500x100.png
bft/static/bft/images/ui/ui-bg_inset-hard_100_f5f8f9_1x100.png
bft/static/bft/images/ui/ui-bg_inset-hard_100_fcfdfd_1x100.png
bft/static/bft/images/ui/ui-icons_217bc0_256x240.png
bft/static/bft/images/ui/ui-icons_2e83ff_256x240.png
bft/static/bft/images/ui/ui-icons_469bdd_256x240.png
bft/static/bft/images/ui/ui-icons_6da8d5_256x240.png
bft/static/bft/images/ui/ui-icons_cd0a0a_256x240.png
bft/static/bft/images/ui/ui-icons_d8e7f3_256x240.png
bft/static/bft/images/ui/ui-icons_f9bd01_256x240.png
bft/static/bft/scripts/admin.js
bft/static/bft/scripts/bft.js
bft/static/bft/scripts/feedback.js
bft/static/bft/scripts/jquery.MultiFile.js
django_bft.egg-info/PKG-INFO
django_bft.egg-info/SOURCES.txt
django_bft.egg-info/dependency_links.txt
django_bft.egg-info/not-zip-safe
django_bft.egg-info/top_level.txt
