Metadata-Version: 1.0
Name: django-bft
Version: 0.2.0
Summary: Big File Transfer Application written in Django
Home-page: http://github.com/django-bft/dango-bft
Author: Jay McEntire
Author-email: jay.mcentire@gmail.com
License: GNU GPL v3
Download-URL: https://github.com/django-bft/dango-bft/downloads
Platform: UNKNOWN
Classifier: Development Status :: 4 - Beta
Classifier: Environment :: Web Environment
Classifier: Framework :: Django
Classifier: Intended Audience :: Developers
Classifier: License :: OSI Approved :: GNU General Public License (GPL)
Classifier: Operating System :: OS Independent
Classifier: Programming Language :: Python
Classifier: Topic :: Software Development :: Libraries :: Python Modules
